core_logging/__init__.py
core_logging/logger_conf.py
core_logging/logger_handler.py
core_logging/logger_service.py
core_logging/logger_utils.py
core_logging/py.typed
turintech_logging-2.0.1.dist-info/METADATA
turintech_logging-2.0.1.dist-info/WHEEL
turintech_logging-2.0.1.dist-info/licenses/LICENSE
turintech_logging-2.0.1.dist-info/RECORD
