Metadata-Version: 2.4
Name: turintech_logging
Version: 2.0.1
Summary: Core Libs files logging
License-Expression: LicenseRef-Turing-Intelligence-Technology-EULA
License-File: LICENSE
Classifier: Development Status :: 5 - Production/Stable
Classifier: License :: Other/Proprietary License
Requires-Python: <3.14,>=3.8
Requires-Dist: loguru<1.0.0,>=0.7.0
Requires-Dist: pydantic<3.0.0,>=2
Requires-Dist: python-dotenv<1.0.0,>=0.21.0
Requires-Dist: turintech-configuration<3.0.0,>=2.0.0a0
Requires-Dist: typing-extensions<5.0.0,>=4.5.0
